veox/__init__.py
veox/api.py
veox/doug.py
veox/dummy.py
veox/io.py
veox/model.py
veox-0.2.0.dist-info/METADATA
veox-0.2.0.dist-info/WHEEL
veox-0.2.0.dist-info/licenses/LICENSE
veox-0.2.0.dist-info/RECORD
