Metadata-Version: 2.4
Name: veox
Version: 0.2.0
Summary: A lightweight client for training and managing models against the DOUG scheduler.
Project-URL: Homepage, https://gitlab.com/veox_client/veox_pip
Project-URL: Repository, https://gitlab.com/veox_client/veox_pip
Project-URL: Documentation, https://gitlab.com/veox_client/veox_pip/-/tree/main/docs
Author: Veox
License-File: LICENSE
Classifier: Intended Audience :: Developers
Classifier: License :: OSI Approved :: MIT License
Classifier: Programming Language :: Python :: 3
Requires-Python: >=3.9
Provides-Extra: dev
Requires-Dist: build; extra == 'dev'
Requires-Dist: pytest; extra == 'dev'
Requires-Dist: pytest-cov; extra == 'dev'
Requires-Dist: twine; extra == 'dev'
